{
  "DataEntityMetadataJson": {
    "{58997F21-DC0E-4742-885A-0F18C14D42F3}": "{\"name\":\"{58997F21-DC0E-4742-885A-0F18C14D42F3}\",\"title\":\"B2B\",\"x-ms-permission\":\"read-write\",\"x-ms-capabilities\":{\"sortRestrictions\":{\"sortable\":true},\"filterRestrictions\":{\"filterable\":true},\"filterFunctionSupport\":[\"eq\",\"ne\",\"substringof\",\"contains\",\"startswith\",\"endswith\"]},\"schema\":{\"type\":\"array\",\"items\":{\"type\":\"object\",\"properties\":{\"Date\":{\"type\":\"string\",\"title\":\"Date\",\"x-ms-sort\":\"none\",\"x-ms-capabilities\":{\"filterFunctions\":[\"eq\",\"ne\",\"substringof\",\"contains\",\"startswith\",\"endswith\"]},\"format\":\"date-time\",\"x-ms-permission\":\"read-write\"},\"Name\":{\"type\":\"string\",\"title\":\"Name\",\"x-ms-sort\":\"none\",\"x-ms-capabilities\":{\"filterFunctions\":[\"eq\",\"ne\",\"substringof\",\"contains\",\"startswith\",\"endswith\"]},\"x-ms-permission\":\"read-write\"},\"Status\":{\"type\":\"string\",\"title\":\"Status\",\"x-ms-sort\":\"none\",\"x-ms-capabilities\":{\"filterFunctions\":[\"eq\",\"ne\",\"substringof\",\"contains\",\"startswith\",\"endswith\"]},\"x-ms-permission\":\"read-write\"},\"__PowerAppsId__\":{\"type\":\"string\",\"title\":\"__PowerAppsId__\",\"x-ms-sort\":\"none\",\"x-ms-capabilities\":{\"filterFunctions\":[\"eq\",\"ne\",\"substringof\",\"contains\",\"startswith\",\"endswith\"]},\"x-ms-keyOrder\":1,\"x-ms-keyType\":\"primary\",\"x-ms-permission\":\"read-only\"}}}}}"
  },
  "EntityName": "B2B_2",
  "TableName": "{58997F21-DC0E-4742-885A-0F18C14D42F3}"
}