{
  "DataEntityMetadataJson": {
    "{C17AA34F-4202-462F-B315-F822F21F1223}": "{\"name\":\"{C17AA34F-4202-462F-B315-F822F21F1223}\",\"title\":\"SpecAct\",\"x-ms-permission\":\"read-write\",\"x-ms-capabilities\":{\"sortRestrictions\":{\"sortable\":true},\"filterRestrictions\":{\"filterable\":true},\"filterFunctionSupport\":[\"eq\",\"ne\",\"substringof\",\"contains\",\"startswith\",\"endswith\"]},\"schema\":{\"type\":\"array\",\"items\":{\"type\":\"object\",\"properties\":{\"Date\":{\"type\":\"string\",\"title\":\"Date\",\"x-ms-sort\":\"none\",\"x-ms-capabilities\":{\"filterFunctions\":[\"eq\",\"ne\",\"substringof\",\"contains\",\"startswith\",\"endswith\"]},\"format\":\"date-time\",\"x-ms-permission\":\"read-write\"},\"Name\":{\"type\":\"string\",\"title\":\"Name\",\"x-ms-sort\":\"none\",\"x-ms-capabilities\":{\"filterFunctions\":[\"eq\",\"ne\",\"substringof\",\"contains\",\"startswith\",\"endswith\"]},\"x-ms-permission\":\"read-write\"},\"Status\":{\"type\":\"string\",\"title\":\"Status\",\"x-ms-sort\":\"none\",\"x-ms-capabilities\":{\"filterFunctions\":[\"eq\",\"ne\",\"substringof\",\"contains\",\"startswith\",\"endswith\"]},\"x-ms-permission\":\"read-write\"},\"Role\":{\"type\":\"string\",\"title\":\"Role\",\"x-ms-sort\":\"none\",\"x-ms-capabilities\":{\"filterFunctions\":[\"eq\",\"ne\",\"substringof\",\"contains\",\"startswith\",\"endswith\"]},\"x-ms-permission\":\"read-write\"},\"Месяц обучения\":{\"type\":\"string\",\"title\":\"Месяц обучения\",\"x-ms-sort\":\"none\",\"x-ms-capabilities\":{\"filterFunctions\":[\"eq\",\"ne\",\"substringof\",\"contains\",\"startswith\",\"endswith\"]},\"x-ms-permission\":\"read-write\"}}}}}"
  },
  "EntityName": "SpecAct",
  "TableName": "{C17AA34F-4202-462F-B315-F822F21F1223}"
}